README.txt
setup.py
pylabstestsupport/__init__.py
pylabstestsupport/helpers.py
pylabstestsupport.egg-info/PKG-INFO
pylabstestsupport.egg-info/SOURCES.txt
pylabstestsupport.egg-info/dependency_links.txt
pylabstestsupport.egg-info/requires.txt
pylabstestsupport.egg-info/top_level.txt