Metadata-Version: 1.0
Name: pylabstestsupport
Version: 0.0.9
Summary: Support for testing pylabs3 code
Home-page: http://pypi.python.org/pypi/pylabstestsupport
Author: Michael Heyvaert
Author-email: release.management@amplidata.com
License: LICENSE.txt
Platform: UNKNOWN
